personfromvid/__init__.py
personfromvid/__main__.py
personfromvid/cli.py
personfromvid/analysis/__init__.py
personfromvid/analysis/closeup_detector.py
personfromvid/analysis/frame_selector.py
personfromvid/analysis/head_angle_classifier.py
personfromvid/analysis/person_builder.py
personfromvid/analysis/person_selector.py
personfromvid/analysis/pose_classifier.py
personfromvid/analysis/quality_assessor.py
personfromvid/core/__init__.py
personfromvid/core/frame_extractor.py
personfromvid/core/pipeline.py
personfromvid/core/state_manager.py
personfromvid/core/temp_manager.py
personfromvid/core/video_processor.py
personfromvid/core/steps/__init__.py
personfromvid/core/steps/base.py
personfromvid/core/steps/closeup_detection.py
personfromvid/core/steps/face_detection.py
personfromvid/core/steps/frame_extraction.py
personfromvid/core/steps/frame_selection.py
personfromvid/core/steps/initialization.py
personfromvid/core/steps/output_generation.py
personfromvid/core/steps/person_building.py
personfromvid/core/steps/person_selection.py
personfromvid/core/steps/pose_analysis.py
personfromvid/core/steps/quality_assessment.py
personfromvid/data/__init__.py
personfromvid/data/config.py
personfromvid/data/constants.py
personfromvid/data/context.py
personfromvid/data/detection_results.py
personfromvid/data/frame_data.py
personfromvid/data/person.py
personfromvid/data/pipeline_state.py
personfromvid/models/__init__.py
personfromvid/models/face_detector.py
personfromvid/models/face_restorer.py
personfromvid/models/head_pose_estimator.py
personfromvid/models/model_configs.py
personfromvid/models/model_manager.py
personfromvid/models/model_utils.py
personfromvid/models/pose_estimator.py
personfromvid/output/__init__.py
personfromvid/output/crop_utils.py
personfromvid/output/image_processor.py
personfromvid/output/image_writer.py
personfromvid/output/naming_convention.py
personfromvid/utils/__init__.py
personfromvid/utils/exceptions.py
personfromvid/utils/formatting.py
personfromvid-1.4.0.dist-info/licenses/LICENSE
personfromvid-1.4.0.dist-info/METADATA
personfromvid-1.4.0.dist-info/WHEEL
personfromvid-1.4.0.dist-info/entry_points.txt
personfromvid-1.4.0.dist-info/top_level.txt
personfromvid-1.4.0.dist-info/RECORD
