Metadata-Version: 2.4
Name: personfromvid
Version: 1.4.0
Summary: Extract and categorize high-quality frames containing people in specific poses from video files
Author: codeprimate
License-Expression: GPL-3.0-or-later
Project-URL: Homepage, https://github.com/codeprimate/personfromvid
Project-URL: Documentation, https://github.com/codeprimate/personfromvid/docs
Project-URL: Repository, https://github.com/codeprimate/personfromvid
Project-URL: Issues, https://github.com/codeprimate/personfromvid/issues
Classifier: Development Status :: 4 - Beta
Classifier: Intended Audience :: Developers
Classifier: Intended Audience :: End Users/Desktop
Classifier: Operating System :: OS Independent
Classifier: Programming Language :: Python :: 3
Classifier: Programming Language :: Python :: 3.8
Classifier: Programming Language :: Python :: 3.9
Classifier: Programming Language :: Python :: 3.10
Classifier: Programming Language :: Python :: 3.11
Classifier: Topic :: Multimedia :: Video
Classifier: Topic :: Scientific/Engineering :: Artificial Intelligence
Classifier: Topic :: Scientific/Engineering :: Image Processing
Requires-Python: >=3.10
License-File: LICENSE
Requires-Dist: opencv-python==4.8.1.78
Requires-Dist: ffmpeg-python==0.2.0
Requires-Dist: Pillow==10.1.0
Requires-Dist: numpy==1.24.4
Requires-Dist: torch==2.1.1
Requires-Dist: torchvision==0.16.1
Requires-Dist: onnxruntime==1.16.3
Requires-Dist: ultralytics==8.0.220
Requires-Dist: safetensors==0.5.3
Requires-Dist: gfpgan>=1.3.8
Requires-Dist: click==8.1.7
Requires-Dist: rich==13.7.0
Requires-Dist: pydantic==2.5.0
Requires-Dist: PyYAML==6.0.1
Requires-Dist: tomli>=2.0.1; python_version < "3.11"
Requires-Dist: requests==2.31.0
Requires-Dist: tqdm==4.66.1
Requires-Dist: platformdirs==4.2.2
Provides-Extra: dev
Requires-Dist: pytest==7.4.3; extra == "dev"
Requires-Dist: pytest-cov==4.1.0; extra == "dev"
Requires-Dist: black==23.11.0; extra == "dev"
Requires-Dist: flake8==6.1.0; extra == "dev"
Requires-Dist: mypy==1.7.1; extra == "dev"
Requires-Dist: pre-commit==3.6.0; extra == "dev"
Requires-Dist: build==1.2.2.post1; extra == "dev"
Requires-Dist: twine==6.1.0; extra == "dev"
Requires-Dist: ruff==0.5.5; extra == "dev"
Provides-Extra: gpu
Requires-Dist: onnxruntime-gpu>=1.15.0; extra == "gpu"
Dynamic: license-file
